MANIFEST.in
README.md
setup.py
csdjango/__init__.py
csdjango.contactform.egg-info/PKG-INFO
csdjango.contactform.egg-info/SOURCES.txt
csdjango.contactform.egg-info/dependency_links.txt
csdjango.contactform.egg-info/entry_points.txt
csdjango.contactform.egg-info/namespace_packages.txt
csdjango.contactform.egg-info/not-zip-safe
csdjango.contactform.egg-info/requires.txt
csdjango.contactform.egg-info/top_level.txt
csdjango/contactform/__init__.py
csdjango/contactform/forms.py
csdjango/contactform/views.py
csdjango/contactform/locale/de/LC_MESSAGES/django.po
csdjango/contactform/locale/es/LC_MESSAGES/django.po
csdjango/contactform/locale/eu/LC_MESSAGES/django.po
csdjango/contactform/templates/contact_form/contact_form.html
csdjango/contactform/templates/contact_form/contact_form.txt
csdjango/contactform/templates/contact_form/contact_form_sent.html
csdjango/contactform/templates/contact_form/contact_form_subject.txt
docs/HISTORY.txt