Metadata-Version: 2.1
Name: csdjango.contactform
Version: 1.3
Summary: i18n ready contact form
Home-page: UNKNOWN
Author: 
Author-email: 
License: UNKNOWN
Platform: UNKNOWN
Classifier: Programming Language :: Python
Classifier: Topic :: Software Development :: Libraries :: Python Modules
